{"ex1": {"mean": 3.5, "var": 2.917}, "ex2": {"hist": "center"}, "ex3": {"sum_2_8": 0.07, "sum_3_7": 0.131, "sum_4_6": 0.191, "sum_5": 0.216}, "ex4": {"mean": 5.8, "var": 3.36, "cov": 0.0}, "ex5": {"hist": "center"}, "ex6": {"max_sum": 2}, "ex7": {"hist": "left-most"}, "ex8": {"hist": "right-center"}, "ex9": {"mean": "increases", "var": "increases", "cov": "stays the same"}, "ex10": {"options": "changing the loaded side from 1 to 6 will yield a higher mean but the same variance"}, "ex11": {"options": "changing the direction of the inequality will change the sign of the covariance"}, "ex12": {"options": "yes, but only if one of the sides is loaded"}}